mdocker/__main__.py
mdocker/interfaces/__init__.py
mdocker/interfaces/models.py
mdocker/models/__init__.py
mdocker/models/image_builder.py
mdocker/tools/__init__.py
mdocker/tools/commands.py
mdocker/tools/messages.py
mdocker-0.3.1.dist-info/LICENSE.md
mdocker-0.3.1.dist-info/METADATA
mdocker-0.3.1.dist-info/WHEEL
mdocker-0.3.1.dist-info/RECORD
