Metadata-Version: 2.1
Name: mdocker
Version: 0.3.1
Summary: Easy-to-use wrapper for multi-platform Docker image builds.
Home-page: https://github.com/seppzer0/mdocker
License: MIT
Keywords: docker,docker-buildx,multi-platform
Author: seppzer0
Requires-Python: >=3.10,<4.0
Classifier: License :: OSI Approved :: MIT License
Classifier: Programming Language :: Python :: 3
Classifier: Programming Language :: Python :: 3.10
Classifier: Programming Language :: Python :: 3.11
Classifier: Programming Language :: Python :: 3.12
Requires-Dist: argparse (>=1.4.0,<2.0.0)
Requires-Dist: pathlib (>=1.0,<2.0)
Requires-Dist: pydantic (>=2.6,<3.0)
Requires-Dist: typing (>=3.7,<4.0)
Project-URL: Repository, https://github.com/seppzer0/mdocker
